bapi_fw/__init__.py
bapi_fw/api.py
bapi_fw/request_handler.py
bapi_fw/routes.py
bapi_fw-0.0.6.dist-info/LICENSE
bapi_fw-0.0.6.dist-info/METADATA
bapi_fw-0.0.6.dist-info/WHEEL
bapi_fw-0.0.6.dist-info/top_level.txt
bapi_fw-0.0.6.dist-info/RECORD
