Metadata-Version: 2.1
Name: bapi-fw
Version: 0.0.6
Summary: UNKNOWN
Home-page: UNKNOWN
Author: Christophe Kafrouni
Author-email: <chris.kafrouni@gmail.com>
License: UNKNOWN
Keywords: python,api,framework,sockets
Platform: UNKNOWN
Classifier: Development Status :: 1 - Planning
Classifier: Intended Audience :: Developers
Classifier: Programming Language :: Python :: 3
Classifier: Operating System :: Unix
Classifier: Operating System :: MacOS :: MacOS X
Classifier: Operating System :: Microsoft :: Windows
License-File: LICENSE
Requires-Dist: pydantic
